YAML_Project_Loader/ContextLoader.py
YAML_Project_Loader/Project.py
YAML_Project_Loader/__init__.py
YAML_Project_Loader-0.0.4.dist-info/METADATA
YAML_Project_Loader-0.0.4.dist-info/RECORD
YAML_Project_Loader-0.0.4.dist-info/WHEEL
YAML_Project_Loader-0.0.4.dist-info/top_level.txt
