Metadata-Version: 2.1
Name: YAML-Project-Loader
Version: 0.0.4
Summary: YAML Project Loader
Home-page: http://fahrerassistenzsysteme.de
Author: FAS GmbH
Author-email: daniel.ramirez@fahrerassistenzsysteme.de
License: UNKNOWN
Project-URL: Internal Repository, http://gogs.kse.local/ramirda/YAML_Project_Loader
Platform: UNKNOWN
Classifier: Topic :: Utilities
Classifier: Topic :: Software Development :: Pre-processors
Classifier: Development Status :: 3 - Alpha
Classifier: Programming Language :: Python :: 2
Classifier: License :: OSI Approved :: MIT License
Classifier: Operating System :: Microsoft :: Windows
